{
  "common": {
    "signIn": "Logga In",
    "signUp": "Registrera dig",
    "home": "Hem"
  },
  "placeholder": {
    "usernameEmail": "Användarnamn/Email",
    "password": "Lösenord",
    "username": "Användarnamn",
    "email": "Email",
    "confirmPassword": "Bekräfta lösenord"
  },
  "signIn": {
    "title": "Logga in till ditt Bridgestarskonto",
    "subtitle": "Ange ditt användarnamn och lösenord",
    "footer": "Har du inget konto?",
    "forgot": "Glömt ditt lösenord?"
  },
  "signUp": {
    "title": "Gå med i Bridgestars väntelista",
    "subtitle": "Fyll i dina användaruppgifter nedan för att skapa ett konto.",
    "footer": "Har du redan ett konto?"
  },
  "reset": {
    "title": "Återställ ditt Bridgestars lösenord",
    "subtitle": "Ange din e-postadress för att återställa ditt lösenord.",
    "resetPassword": "Återställ Lösenord",
    "footer": "Ångrat dig?",
    "button": "Gå Tillbaka"
  }
}
